ddco_lab/week2/circuit2/circuit2.v
module circuit2(A,B,C,D);
input A,B,C;
output D;
wire w1;
and G1(w1,C,B);
or (D,w1,A);
endmodule

ddco_lab/week2/circuit2/circuit2_tb.v
module circuit2_tb;
wire D;
reg A,B,C;
circuit2 M1(A,B,C,D);
initial
begin
$dumpfile("circuit2.vcd");
$dumpvars(1,circuit2_tb);

A=0;B=0;C=0;
#1 A=0;B=0;C=1;
#1 A=0;B=1;C=0;
#1 A=0;B=1;C=1;
#1 A=1;B=0;C=0;
#1 A=1;B=0;C=1;
#1 A=1;B=1;C=0;
#1 A=1;B=1;C=1;
#1;
end
initial
begin
$monitor($time," A=%b B=%b C=%b D=%b",A,B,C,D);
end
endmodule

ddco_lab/week2/circuit2/circuit2.vcd
$date
	Thu Feb 11 22:42:38 2016
$end
$version
	Icarus Verilog
$end
$timescale
	1s
$end
$scope module circuit2_tb $end
$var wire 1 ! D $end
$var reg 1 " A $end
$var reg 1 # B $end
$var reg 1 $ C $end
$upscope $end
$enddefinitions $end
#0
$dumpvars
0$
0#
0"
0!
$end
#20
1$
#40
0$
1#
#60
1!
1$
#80
0$
0#
1"
#100
1$
#120
0$
1#
#140
1$
