ddco_lab/week2/circuit3/circuit3.v
module circuit3(A,B,C,D);
input A,B,C;
output D;
wire w1,w2,w3;
and G1(w1,C,B);
or G2(w2,A,w1);
and G3(w3,A,B);
or G4(D,w2,w3);
endmodule

ddco_lab/week2/circuit3/circuit3_tb.v
module circuit3_tb;
reg A,B,C;
wire D;
circuit3 M1(A,B,C,D);
initial
begin
A=0;B=0;C=0;
#1 A=0;B=0;C=1;
#1 A=0;B=1;C=0;
#1 A=0;B=1;C=1;
#1 A=1;B=0;C=0;
#1 A=1;B=0;C=1;
#1 A=1;B=1;C=0;
#1 A=1;B=1;C=1;
#1;
end
initial
begin
$monitor($time," A=%b B=%b C=%b D=%b",A,B,C,D);
end
initial
begin
$dumpfile("circuit3.vcd");
$dumpvars(1,circuit3_tb);
end
endmodule

ddco_lab/week2/circuit3/circuit3.vcd
$date
	Thu Feb 11 22:48:07 2016
$end
$version
	Icarus Verilog
$end
$timescale
	1s
$end
$scope module circuit3_tb $end
$var wire 1 ! D $end
$var reg 1 " A $end
$var reg 1 # B $end
$var reg 1 $ C $end
$upscope $end
$enddefinitions $end
#0
$dumpvars
0$
0#
0"
0!
$end
#1
1$
#2
0$
1#
#3
1!
1$
#4
0$
0#
1"
#5
1$
#6
0$
1#
#7
1$
